portmap/__init__.py
portmap/__version__.py
portmap/app.py
portmap/cli.py
portmap/util.py
portmap-0.0.2.dist-info/LICENSE
portmap-0.0.2.dist-info/METADATA
portmap-0.0.2.dist-info/WHEEL
portmap-0.0.2.dist-info/entry_points.txt
portmap-0.0.2.dist-info/top_level.txt
portmap-0.0.2.dist-info/RECORD
