Metadata-Version: 2.1
Name: portmap
Version: 0.0.2
Summary: Command line tool for CAP portmap
Home-page: https://gitlab.dudaji.com
Author: dudaji
Author-email: shhong@dudaji.com
License: UNKNOWN
Platform: UNKNOWN
Classifier: Programming Language :: Python
Classifier: Programming Language :: Python :: 2
Classifier: Programming Language :: Python :: 2.7
Classifier: Programming Language :: Python :: 3
Classifier: Programming Language :: Python :: 3.5
Classifier: Programming Language :: Python :: 3.6
Classifier: Programming Language :: Python :: 3.7
Requires-Python: >=2.7, !=3.0.*, !=3.1.*, !=3.2.*, !=3.3.*, !=3.4.*
Requires-Dist: shortuuid (==1.0.1)
Requires-Dist: kubernetes (==11.0.0)
Requires-Dist: fire (==0.3.1)
Requires-Dist: Flask (==1.1.2)
Requires-Dist: Flask-RESTful (==0.3.8)
Requires-Dist: terminaltables (==3.1.0)
